{
  "generator-jhipster": {
    "authenticationType": "jwt",
    "cacheProvider": "ehcache",
    "clientFramework": "react",
    "serverPort": "9001",
    "serviceDiscoveryType": false,
    "skipUserManagement": false,
    "withAdminUi": true,
    "baseName": "SimplifyMarketplace",
    "buildTool": "maven",
    "databaseType": "mongodb",
    "devDatabaseType": "mongodb",
    "enableHibernateCache": false,
    "enableSwaggerCodegen": true,
    "enableTranslation": true,
    "jhiPrefix": "jhi",
    "languages": ["en"],
    "messageBroker": false,
    "prodDatabaseType": "mongodb",
    "searchEngine": false,
    "skipClient": false,
    "testFrameworks": [],
    "websocket": false,
    "applicationType": "monolith",
    "clientPackageManager": "npm",
    "packageName": "com.simplify.marketplace",
    "packageFolder": "com/simplify/marketplace",
    "jhipsterVersion": "7.1.0",
    "skipServer": false,
    "dtoSuffix": "DTO",
    "entitySuffix": "",
    "reactive": false,
    "clientTheme": "none",
    "clientThemeVariant": "",
    "applicationIndex": 0,
    "entities": ["OTP", "OTPAttempt", "Worker", "JobPreference", "PreferredCity", "Education", "Employment", "Address"],
    "skipCheckLengthOfIdentifier": false,
    "skipFakeData": false,
    "blueprints": [],
    "otherModules": [],
    "pages": [],
    "nativeLanguage": "en",
    "creationTimestamp": 1626334019849,
    "jwtSecretKey": "YTcxZTZmZWFmYzdkYTM2YTczNDZhNGJmNTAxOWEwNWZhNzFmZjUzNjZhZTFkNGIzYTEwNTZlMzcwYmQ4N2YyMzRlY2JhMzg1MWJhZWQ3MjIwNTk4NjBkZDhjOWNiOTUwNzYyODZhYjlmMTNhNDA0YTllMjkwMzc4MmZkNzQzMzc=",
    "devServerPort": 9060,
    "lastLiquibaseTimestamp": 1626334499000
  }
}
